object_watchdog/__init__.py
object_watchdog/watchdog.py
object_watchdog-0.0.2.dist-info/METADATA
object_watchdog-0.0.2.dist-info/WHEEL
object_watchdog-0.0.2.dist-info/top_level.txt
object_watchdog-0.0.2.dist-info/RECORD
