Metadata-Version: 2.1
Name: object-watchdog
Version: 0.0.2
Summary: Watch Python object for changes in runtime and launch callbacks
Home-page: https://github.com/cr0hn/object-watchdog
License: License :: OSI Approved :: BSD License
Keywords: monitor,watchdog,metaclass
Platform: UNKNOWN
Classifier: Programming Language :: Python :: 3.6
Classifier: Programming Language :: Python :: 3.7
Classifier: Programming Language :: Python :: 3.8
Classifier: Programming Language :: Python :: 3.9
Classifier: Programming Language :: Python :: Implementation :: PyPy
